sand/__init__.py
sand/__main__.py
sand/app.py
sand/client.py
sand/commands/__init__.py
sand/commands/load.py
sand/config.default.yml
sand/config.py
sand/container.py
sand/controllers/__init__.py
sand/controllers/assistant.py
sand/controllers/helpers/__init__.py
sand/controllers/helpers/upload.py
sand/controllers/project.py
sand/controllers/search.py
sand/controllers/settings.py
sand/controllers/table.py
sand/controllers/transformation.py
sand/deserializer.py
sand/extension_interface/__init__.py
sand/extension_interface/assistant.py
sand/extension_interface/export.py
sand/extension_interface/search.py
sand/extensions/__init__.py
sand/extensions/assistants/__init__.py
sand/extensions/assistants/mtab.py
sand/extensions/search/__init__.py
sand/extensions/search/aggregated_search.py
sand/extensions/search/default_search.py
sand/extensions/search/wikidata_search.py
sand/extensions/wikidata.py
sand/helpers/__init__.py
sand/helpers/dependency_injection.py
sand/helpers/mapping_utils.py
sand/helpers/namespace.py
sand/helpers/service_provider.py
sand/helpers/tree_utils.py
sand/models/__init__.py
sand/models/base.py
sand/models/entity.py
sand/models/ontology.py
sand/models/project.py
sand/models/semantic_model.py
sand/models/table.py
sand/models/table.pyi
sand/models/transformation.py
sand/models/uploading_table.py.deprecated
sand/serializer.py
sand/www/asset-manifest.json
sand/www/favicon.ico
sand/www/index.html
sand/www/logo192.png
sand/www/logo512.png
sand/www/manifest.json
sand/www/robots.txt
sand/www/static/css/2.db8c2148.chunk.css
sand/www/static/css/2.db8c2148.chunk.css.map
sand/www/static/css/main.8470bb9a.chunk.css
sand/www/static/css/main.8470bb9a.chunk.css.map
sand/www/static/js/2.94957aba.chunk.js
sand/www/static/js/2.94957aba.chunk.js.LICENSE.txt
sand/www/static/js/2.94957aba.chunk.js.map
sand/www/static/js/3.0d10569b.chunk.js
sand/www/static/js/3.0d10569b.chunk.js.map
sand/www/static/js/main.d022dc78.chunk.js
sand/www/static/js/main.d022dc78.chunk.js.map
web_sand-4.3.1.dist-info/METADATA
web_sand-4.3.1.dist-info/WHEEL
web_sand-4.3.1.dist-info/entry_points.txt
web_sand-4.3.1.dist-info/RECORD
