Metadata-Version: 2.1
Name: web-sand
Version: 4.3.1
Summary: UI for browsing/editing semantic descriptions
Home-page: https://github.com/usc-isi-i2/sand
License: MIT
Author: Binh Vu
Author-email: binh@toan2.com
Requires-Python: >=3.10,<3.14
Classifier: License :: OSI Approved :: MIT License
Classifier: Programming Language :: Python :: 3
Classifier: Programming Language :: Python :: 3.10
Classifier: Programming Language :: Python :: 3.11
Classifier: Programming Language :: Python :: 3.12
Classifier: Programming Language :: Python :: 3.13
Requires-Dist: RestrictedPython (>=8.0,<9.0)
Requires-Dist: dependency-injector (>=4.41.0,<5.0.0)
Requires-Dist: flask (>=3.0.0,<4.0.0)
Requires-Dist: gena (>=1.7.1,<2.0.0)
Requires-Dist: kgdata (>=7.0.4,<8.0.0)
Requires-Dist: lat_lon_parser (>=1.3.0,<2.0.0)
Requires-Dist: loguru (>=0.7.0,<0.8.0)
Requires-Dist: nh3 (>=0.2.13,<0.3.0)
Requires-Dist: orjson (>=3.9.0,<4.0.0)
Requires-Dist: peewee (>=3.15.2,<4.0.0)
Requires-Dist: python-dotenv (>=0.19.0,<0.20.0)
Requires-Dist: rsoup (>=3.1.7,<4.0.0)
Requires-Dist: sem-desc (>=6.12.0,<7.0.0)
Requires-Dist: tornado (>=6.2,<7.0)
Project-URL: Repository, https://github.com/usc-isi-i2/sand
